telemetrydeckpy/__init__.py
telemetrydeckpy/signal.py
telemetrydeckpy/telemetrydeck.py
tests/__init__.py
tests/signal_test.py
tests/telemetrydeck_test.py
telemetrydeckpy-1.0.0.dist-info/LICENSE
telemetrydeckpy-1.0.0.dist-info/METADATA
telemetrydeckpy-1.0.0.dist-info/WHEEL
telemetrydeckpy-1.0.0.dist-info/top_level.txt
telemetrydeckpy-1.0.0.dist-info/RECORD
