Metadata-Version: 2.1
Name: telemetrydeckpy
Version: 1.0.0
Summary: The TelemetryDeck API the pythonic way
Author: Thore D. Jahn
Author-email: python@kurzgedanke.me
License: MIT
Keywords: telemetrydeck,api,tracking
Classifier: Programming Language :: Python :: 3
Requires-Python: >=3.10
License-File: LICENSE
Requires-Dist: requests
